<?xml version="1.0" encoding="UTF-8"?><record_update table="sys_metadata_link">
    <sys_metadata_link action="INSERT_OR_UPDATE">
        <directory>unload</directory>
        <documentkey>b85d44954a3623120004689b2d5dd60a</documentkey>
        <payload><![CDATA[<?xml version="1.0" encoding="UTF-8"?><record_update table="sys_user_group">
    <sys_user_group action="INSERT_OR_UPDATE">
        <active>true</active>
        <cost_center/>
        <default_assignee/>
        <description>CAB approvers</description>
        <email/>
        <exclude_manager>false</exclude_manager>
        <include_members>false</include_members>
        <manager/>
        <name>CAB Approval</name>
        <parent/>
        <roles/>
        <source/>
        <sys_created_by>admin</sys_created_by>
        <sys_created_on>2011-09-30 16:30:34</sys_created_on>
        <sys_id>b85d44954a3623120004689b2d5dd60a</sys_id>
        <sys_mod_count>0</sys_mod_count>
        <sys_updated_by>admin</sys_updated_by>
        <sys_updated_on>2011-09-30 16:30:34</sys_updated_on>
        <type>1cb8ab9bff500200158bffffffffff62</type>
    </sys_user_group>
</record_update>
]]></payload>
        <sys_class_name>sys_metadata_link</sys_class_name>
        <sys_created_by>admin</sys_created_by>
        <sys_created_on>2022-11-14 08:51:09</sys_created_on>
        <sys_id>768d9e972f0f5550660cbcb62799b63f</sys_id>
        <sys_mod_count>0</sys_mod_count>
        <sys_name>CAB Approval</sys_name>
        <sys_package display_value="Cisco BCS Operational Insights" source="x_caci_cisco_bcs">56b8d9362f3310108956ea5ef699b62d</sys_package>
        <sys_policy/>
        <sys_scope display_value="Cisco BCS Operational Insights">56b8d9362f3310108956ea5ef699b62d</sys_scope>
        <sys_update_name>sys_metadata_link_768d9e972f0f5550660cbcb62799b63f</sys_update_name>
        <sys_updated_by>admin</sys_updated_by>
        <sys_updated_on>2022-11-14 08:51:09</sys_updated_on>
        <tablename>sys_user_group</tablename>
    </sys_metadata_link>
</record_update>
